MANIFEST.in
setup.py
mozpool/__init__.py
mozpool/async.py
mozpool/config.ini.dist
mozpool/config.py
mozpool/statedriver.py
mozpool/statemachine.py
mozpool/util.py
mozpool.egg-info/PKG-INFO
mozpool.egg-info/SOURCES.txt
mozpool.egg-info/dependency_links.txt
mozpool.egg-info/entry_points.txt
mozpool.egg-info/requires.txt
mozpool.egg-info/top_level.txt
mozpool/bmm/__init__.py
mozpool/bmm/api.py
mozpool/bmm/handlers.py
mozpool/bmm/ping.py
mozpool/bmm/pxe.py
mozpool/bmm/relay.py
mozpool/bmm/scripts.py
mozpool/bmm/sut.py
mozpool/db/__init__.py
mozpool/db/base.py
mozpool/db/device_requests.py
mozpool/db/devices.py
mozpool/db/environments.py
mozpool/db/exceptions.py
mozpool/db/images.py
mozpool/db/imaging_servers.py
mozpool/db/inventorysync.py
mozpool/db/model.py
mozpool/db/pool.py
mozpool/db/pxe_configs.py
mozpool/db/relay_boards.py
mozpool/db/requests.py
mozpool/db/scripts.py
mozpool/html/index.html
mozpool/html/ui/bmm.html
mozpool/html/ui/index.html
mozpool/html/ui/lifeguard.html
mozpool/html/ui/log.html
mozpool/html/ui/mozpool.html
mozpool/html/ui/css/ui.css
mozpool/html/ui/js/bmm.js
mozpool/html/ui/js/controllers.js
mozpool/html/ui/js/lifeguard.js
mozpool/html/ui/js/log.js
mozpool/html/ui/js/models.js
mozpool/html/ui/js/mozpool.js
mozpool/html/ui/js/ui.js
mozpool/html/ui/js/views-controls.js
mozpool/html/ui/js/views-header.js
mozpool/html/ui/js/views-logfiles.js
mozpool/html/ui/js/views-tables.js
mozpool/html/ui/js/views-toolbar.js
mozpool/html/ui/js/deps/load-min.js
mozpool/lifeguard/__init__.py
mozpool/lifeguard/devicemachine.py
mozpool/lifeguard/handlers.py
mozpool/lifeguard/inventorysync.py
mozpool/mozpool/__init__.py
mozpool/mozpool/handlers.py
mozpool/mozpool/requestmachine.py
mozpool/test/__init__.py
mozpool/test/fakedevices.py
mozpool/test/fakerelay.py
mozpool/test/util.py
mozpool/test/integration/__init__.py
mozpool/test/integration/test_devicemachine.py
mozpool/test/integration/test_requestmachine.py
mozpool/test/integration/test_startup.py
mozpool/test/unit/__init__.py
mozpool/test/unit/test_async.py
mozpool/test/unit/test_config.py
mozpool/test/unit/test_statemachine.py
mozpool/test/unit/test_util.py
mozpool/test/unit/bmm/__init__.py
