Metadata-Version: 1.0
Name: mozpool
Version: 4.1.3
Summary: System to manage a pool of cranky mobile devices
Home-page: http://hg.mozilla.org/build/mozpool
Author: Ted Mielczarek, Mark Côté, Dustin Mitchell
Author-email: ted@mielczarek.org
License: UNKNOWN
Platform: UNKNOWN
